{
  "background": "#1a1a1a",
  "foreground": "#ffffff",
  "card": "#222222",
  "card-foreground": "#ffffff",
  "popover": "#222222",
  "popover-foreground": "#ffffff",
  "primary": "#cc66bb",
  "primary-foreground": "#ffffff",
  "primary-light": "#882255",
  "secondary": "#2195d6",
  "secondary-foreground": "#ffffff",
  "muted": "#333333",
  "muted-foreground": "#999999",
  "accent": "#882255",
  "accent-foreground": "#ffffff",
  "destructive": "#dc2626",
  "destructive-foreground": "#ffffff",
  "border": "#333333",
  "input": "#333333",
  "ring": "#aa4499",
  "chart-1": "#aa4499",
  "chart-2": "#882255",
  "chart-3": "#2195d6",
  "chart-4": "#4e778e",
  "chart-5": "#dc2626",
  "sidebar": "#222222",
  "sidebar-foreground": "#ffffff",
  "sidebar-primary": "#aa4499",
  "sidebar-primary-foreground": "#ffffff",
  "sidebar-accent": "#882255",
  "sidebar-accent-foreground": "#ffffff",
  "sidebar-border": "#333333",
  "sidebar-ring": "#aa4499",
  "radius": "0.75rem"
}
